resumejson_converter/__init__.py
resumejson_converter/filters.py
resumejson_converter/generators/__init__.py
resumejson_converter/generators/html.py
resumejson_converter/generators/pdf.py
resumejson_converter/utils/__init__.py
resumejson_converter/utils/json.py
resumejson_converter/utils/templates.py
resumejson_converter-0.3.data/scripts/resumejson_converter
resumejson_converter-0.3.dist-info/LICENSE
resumejson_converter-0.3.dist-info/METADATA
resumejson_converter-0.3.dist-info/WHEEL
resumejson_converter-0.3.dist-info/top_level.txt
resumejson_converter-0.3.dist-info/RECORD
