Metadata-Version: 2.1
Name: resumejson-converter
Version: 0.3
Summary: A small package for convert json resume with templating to html and pdf
Home-page: https://git.neodarz.net/neodarz/resumejson_converter.git
Author: neodarz
Author-email: neodarz@neodarz.net
License: UNKNOWN
Platform: UNKNOWN
Classifier: Programming Language :: Python :: 3
Classifier: License :: OSI Approved :: GNU Lesser General Public License v3 (LGPLv3)
